[
  {
    "_id": "6a056b0b79d94845af2c6b85",
    "userId": "6a02d758ab5adcc1eb8b71b5",
    "items": [
      {
        "productId": "6a05634bf3a08e3de0db9319",
        "qty": 1,
        "_id": "6a056b2b79d94845af2c6b8a"
      },
      {
        "productId": "6a05634bf3a08e3de0db931d",
        "qty": 1,
        "_id": "6a05772b79d94845af2c6b96"
      },
      {
        "productId": "6a05634bf3a08e3de0db9323",
        "qty": 1,
        "_id": "6a05997e5a0b4efad105ff04"
      }
    ],
    "createdAt": "2026-05-14T06:26:19.704Z",
    "updatedAt": "2026-05-14T09:44:30.113Z",
    "__v": 5
  },
  {
    "_id": "6a05b851ca9e951e0fd13302",
    "userId": "6a056361793e01d720dec991",
    "items": [
      {
        "productId": "6a05634bf3a08e3de0db931a",
        "qty": 2,
        "_id": "6a0d9421af39736c1cbf029b"
      }
    ],
    "createdAt": "2026-05-14T11:56:01.886Z",
    "updatedAt": "2026-05-20T10:59:47.345Z",
    "__v": 13
  },
  {
    "_id": "6a05c42f332aa990118648ba",
    "userId": "6a056361793e01d720dec992",
    "items": [],
    "createdAt": "2026-05-14T12:46:39.688Z",
    "updatedAt": "2026-05-20T13:56:11.963Z",
    "__v": 32
  },
  {
    "_id": "6a06b34db09c723cf2a12104",
    "userId": "6a02d758ab5adcc1eb8b71b6",
    "items": [
      {
        "productId": "6a05634bf3a08e3de0db931a",
        "qty": 1,
        "_id": "6a0709114bde67d16e77af39"
      }
    ],
    "createdAt": "2026-05-15T05:46:53.996Z",
    "updatedAt": "2026-05-15T11:52:49.351Z",
    "__v": 8
  },
  {
    "_id": "6a0709294bde67d16e77af3b",
    "userId": "6a056361793e01d720dec994",
    "items": [],
    "createdAt": "2026-05-15T11:53:13.574Z",
    "updatedAt": "2026-05-18T10:00:19.299Z",
    "__v": 8
  }
]